pyldl/__init__.py
pyldl/metrics.py
pyldl/utils.py
pyldl/algorithms/__init__.py
pyldl/algorithms/_algorithm_adaptation.py
pyldl/algorithms/_classifier.py
pyldl/algorithms/_ensemble.py
pyldl/algorithms/_incomplete.py
pyldl/algorithms/_label_enhancement.py
pyldl/algorithms/_ldl_da.py
pyldl/algorithms/_ldl_dpa.py
pyldl/algorithms/_ldl_lrr.py
pyldl/algorithms/_ldl_scl.py
pyldl/algorithms/_ldlf.py
pyldl/algorithms/_problem_transformation.py
pyldl/algorithms/_specialized_algorithms.py
pyldl/algorithms/_ssg_ldl.py
pyldl/algorithms/base.py
pyldl/applications/__init__.py
pyldl/applications/emphasis_selection.py
pyldl/applications/facial_emotion_recognition.py
pyldl/applications/lesion_counting.py
pyldl/matlab_algorithms/AA_BP_fit.m
pyldl/matlab_algorithms/AA_BP_predict.m
pyldl/matlab_algorithms/AA_KNN.m
pyldl/matlab_algorithms/BFGS_Process.m
pyldl/matlab_algorithms/PT_Bayes_fit.m
pyldl/matlab_algorithms/PT_Bayes_predict.m
pyldl/matlab_algorithms/PT_SVM_fit.m
pyldl/matlab_algorithms/PT_SVM_predict.m
pyldl/matlab_algorithms/SA_BFGS_fit.m
pyldl/matlab_algorithms/SA_BFGS_predict.m
pyldl/matlab_algorithms/SA_IIS_fit.m
pyldl/matlab_algorithms/SA_IIS_predict.m
pyldl/matlab_algorithms/__init__.py
python_ldl-0.0.3.dist-info/LICENSE
python_ldl-0.0.3.dist-info/METADATA
python_ldl-0.0.3.dist-info/WHEEL
python_ldl-0.0.3.dist-info/top_level.txt
python_ldl-0.0.3.dist-info/RECORD
