Metadata-Version: 2.1
Name: python-ldl
Version: 0.0.3
Summary: Label distribution learning (LDL) and label enhancement (LE) toolkit implemented in python.
Home-page: https://github.com/SpriteMisaka/PyLDL
Author: SpriteMisaka
Author-email: SpriteMisaka@gmail.com
Classifier: Programming Language :: Python :: 3
Classifier: License :: OSI Approved :: MIT License
Classifier: Operating System :: OS Independent
Requires-Python: >=3
License-File: LICENSE
Requires-Dist: matplotlib
Requires-Dist: numpy
Requires-Dist: qpsolvers
Requires-Dist: quadprog
Requires-Dist: scikit-fuzzy
Requires-Dist: scikit-learn
Requires-Dist: scipy
Requires-Dist: tensorflow
Requires-Dist: tensorflow-probability
